[
    {
        "id": "394a6a185f1040ee9d852f1f8c80a45b",
        "platform": "CodeChef",
        "title": "Monday Munch - DSA Challenge 28",
        "url": "https://www.codechef.com/DSAMONDAY28",
        "start_time": "2026-03-09T18:00:00+05:30",
        "duration": 10800
    },
    {
        "id": "354e22b84f1f4177a249b9226415dea8",
        "platform": "CodeChef",
        "title": "Starters 229",
        "url": "https://www.codechef.com/START229",
        "start_time": "2026-03-11T20:00:00+05:30",
        "duration": 7200
    },
    {
        "id": "5474d4fc7f6b438a8a511deddf74a5f5",
        "platform": "CodeChef",
        "title": "Starters 230",
        "url": "https://www.codechef.com/START230",
        "start_time": "2026-03-18T20:00:00+05:30",
        "duration": 7200
    },
    {
        "id": "5cc92482f3334a68be2803deb6aa3552",
        "platform": "CodeChef",
        "title": "Starters 231",
        "url": "https://www.codechef.com/START231",
        "start_time": "2026-03-25T20:00:00+05:30",
        "duration": 7200
    },
    {
        "id": "9787813aee2746c2869e974e9b41abd4",
        "platform": "Codeforces",
        "title": "Educational Codeforces Round 188 (Rated for Div. 2)",
        "url": "https://codeforces.com/contests/2204",
        "start_time": "2026-03-16T20:05:00+05:30",
        "duration": 7200
    },
    {
        "id": "c83505dc7eed46e0861937366b6cecbd",
        "platform": "Codeforces",
        "title": "Codeforces Round (Div. 2)",
        "url": "https://codeforces.com/contests/2208",
        "start_time": "2026-03-14T20:05:00+05:30",
        "duration": 7200
    },
    {
        "id": "52d9e559b6134c22aff282bf49592eb2",
        "platform": "LeetCode",
        "title": "Weekly Contest 493",
        "url": "https://leetcode.com/contest/weekly-contest-493",
        "start_time": "2026-03-15T08:00:00+05:30",
        "duration": 5400
    },
    {
        "id": "607d06c1dc8c4352b23d55db9c66972d",
        "platform": "LeetCode",
        "title": "Biweekly Contest 178",
        "url": "https://leetcode.com/contest/biweekly-contest-178",
        "start_time": "2026-03-14T20:00:00+05:30",
        "duration": 5400
    },
    {
        "id": "64c0bc12746c4463b402ba4b69610d08",
        "platform": "AtCoder",
        "title": "UNIQUE VISION Programming Contest 2026 Spring (AtCoder Heuristic Contest 062)",
        "url": "https://atcoder.jp/contests/ahc062",
        "start_time": "2026-03-14T15:00:00+09:00",
        "duration": 14400
    },
    {
        "id": "a7f0a0b43c2f4cc7bb0f416b04509b9d",
        "platform": "AtCoder",
        "title": "AtCoder Beginner Contest 449",
        "url": "https://atcoder.jp/contests/abc449",
        "start_time": "2026-03-14T21:00:00+09:00",
        "duration": 6000
    },
    {
        "id": "27c7335041034852922a735724438611",
        "platform": "AtCoder",
        "title": "AtCoder Beginner Contest 450",
        "url": "https://atcoder.jp/contests/abc450",
        "start_time": "2026-03-21T21:00:00+09:00",
        "duration": 6000
    },
    {
        "id": "1fad089cd1c24736bd943cdf42ea7adc",
        "platform": "AtCoder",
        "title": "AtCoder Regular Contest++ 216",
        "url": "https://atcoder.jp/contests/arc216",
        "start_time": "2026-03-22T21:00:00+09:00",
        "duration": 9000
    },
    {
        "id": "3c901b7704d04f0fa28be5c731d30253",
        "platform": "AtCoder",
        "title": "AtCoder Beginner Contest 451",
        "url": "https://atcoder.jp/contests/abc451",
        "start_time": "2026-03-28T21:00:00+09:00",
        "duration": 6000
    },
    {
        "id": "0f6e032a1b164ae8803b2d197d14bec9",
        "platform": "AtCoder",
        "title": "AtCoder Grand Contest 077",
        "url": "https://atcoder.jp/contests/agc077",
        "start_time": "2026-03-29T21:00:00+09:00",
        "duration": 10800
    },
    {
        "id": "e34cccf199a047619eddcb9531eeab8e",
        "platform": "AtCoder",
        "title": "AtCoder Heuristic Contest 063",
        "url": "https://atcoder.jp/contests/ahc063",
        "start_time": "2026-04-03T19:00:00+09:00",
        "duration": 864000
    },
    {
        "id": "617f1a099ee54a90870d1e6e7238ae82",
        "platform": "AtCoder",
        "title": "AtCoder Beginner Contest 452",
        "url": "https://atcoder.jp/contests/abc452",
        "start_time": "2026-04-04T21:00:00+09:00",
        "duration": 6000
    }
]