[
    {
        "id": "7725bdd2f9c34df281e58faa9c790946",
        "platform": "CodeChef",
        "title": "Starters 180",
        "url": "https://www.codechef.com/START180",
        "start_time": "2025-04-02T20:00:00+05:30",
        "duration": 7200
    },
    {
        "id": "82094647b44044928b2b7639ead8b650",
        "platform": "CodeChef",
        "title": "Starters 181",
        "url": "https://www.codechef.com/START181",
        "start_time": "2025-04-09T20:00:00+05:30",
        "duration": 7200
    },
    {
        "id": "faff212e67104e8eb80726d4df397467",
        "platform": "Codeforces",
        "title": "Codeforces Round (Div. 4)",
        "url": "https://codeforces.com/contests/2094",
        "start_time": "2025-04-13T21:05:00+05:30",
        "duration": 8100
    },
    {
        "id": "a8e3b21556ef42b48455278a2df501a5",
        "platform": "Codeforces",
        "title": "Codeforces Round (Div. 3)",
        "url": "https://codeforces.com/contests/2093",
        "start_time": "2025-04-08T20:05:00+05:30",
        "duration": 8100
    },
    {
        "id": "5277c2c6263447be9743ce1310654482",
        "platform": "Codeforces",
        "title": "Kotlin Heroes: Episode 12",
        "url": "https://codeforces.com/contests/2087",
        "start_time": "2025-04-07T20:05:00+05:30",
        "duration": 9000
    },
    {
        "id": "5064c44eaa7746d6af9c533a14c1d26a",
        "platform": "Codeforces",
        "title": "Teza Round 1 (Codeforces Round 1015, Div. 1 + Div. 2)",
        "url": "https://codeforces.com/contests/2084",
        "start_time": "2025-04-05T20:05:00+05:30",
        "duration": 10800
    },
    {
        "id": "cf2beea0e8f94bdbb2dbab43817dabc8",
        "platform": "Codeforces",
        "title": "Educational Codeforces Round 177 (Rated for Div. 2)",
        "url": "https://codeforces.com/contests/2086",
        "start_time": "2025-04-03T20:05:00+05:30",
        "duration": 7200
    },
    {
        "id": "a28d04293cdf495b8709b90c8439a6be",
        "platform": "Codeforces",
        "title": "April Fools Day Contest 2025",
        "url": "https://codeforces.com/contests/2095",
        "start_time": "2025-04-01T20:05:00+05:30",
        "duration": 7200
    },
    {
        "id": "19b72b6eda304c33afc6fca554092e14",
        "platform": "Codeforces",
        "title": "Kotlin Heroes: Practice 12",
        "url": "https://codeforces.com/contests/2088",
        "start_time": "2025-03-31T19:05:00+05:30",
        "duration": 604800
    },
    {
        "id": "76fe2d5155894c338dbe397823390f8f",
        "platform": "GeeksforGeeks",
        "title": "GfG Weekly - 200 [Rated Contest]",
        "url": "https://practice.geeksforgeeks.org/contest/gfg-weekly-200-rated-contest",
        "start_time": "2025-03-31T00:30:00+05:30",
        "duration": 5400
    },
    {
        "id": "e825e1460426429ba5fae8b875a055c4",
        "platform": "GeeksforGeeks",
        "title": "GfG Weekly - 201 [Rated Contest]",
        "url": "https://practice.geeksforgeeks.org/contest/gfg-weekly-201-rated-contest",
        "start_time": "2025-04-07T00:30:00+05:30",
        "duration": 5400
    },
    {
        "id": "08df42ce94c24921969d6cbd8bfe80e8",
        "platform": "GeeksforGeeks",
        "title": "GfG Weekly - 202 [Rated Contest]",
        "url": "https://practice.geeksforgeeks.org/contest/gfg-weekly-202-rated-contest",
        "start_time": "2025-04-14T00:30:00+05:30",
        "duration": 5400
    },
    {
        "id": "cbe81642fd0944c99c4f78847ea6eeeb",
        "platform": "GeeksforGeeks",
        "title": "Job-A-thon 44 Hiring Challenge",
        "url": "https://practice.geeksforgeeks.org/contest/job-a-thon-44-hiring-challenge",
        "start_time": "2025-04-22T01:30:00+05:30",
        "duration": 9000
    },
    {
        "id": "d4cf0d8cb6634d32978dec8eed31f416",
        "platform": "LeetCode",
        "title": "Biweekly Contest 154",
        "url": "https://leetcode.com/contest/biweekly-contest-154",
        "start_time": "2025-04-12T20:00:00+05:30",
        "duration": 5400
    },
    {
        "id": "2bacdffe9a0b4500abea79484c7f9215",
        "platform": "LeetCode",
        "title": "Weekly Contest 444",
        "url": "https://leetcode.com/contest/weekly-contest-444",
        "start_time": "2025-04-06T08:00:00+05:30",
        "duration": 5400
    },
    {
        "id": "e2ed25015e12448d84f42c3e77d31770",
        "platform": "AtCoder",
        "title": "AtCoder Grand Contest 071",
        "url": "https://atcoder.jp/contests/agc071",
        "start_time": "2025-03-30T21:00:00+09:00",
        "duration": 10800
    },
    {
        "id": "839518a8f3964704b496dbf768492d19",
        "platform": "AtCoder",
        "title": "AtCoder Beginner Contest 400",
        "url": "https://atcoder.jp/contests/abc400",
        "start_time": "2025-04-05T21:00:00+09:00",
        "duration": 6000
    },
    {
        "id": "7171a47883244975b69998f749ce9d8c",
        "platform": "AtCoder",
        "title": "AtCoder Regular Contest 196 (Div. 1)",
        "url": "https://atcoder.jp/contests/arc196",
        "start_time": "2025-04-06T21:00:00+09:00",
        "duration": 9000
    },
    {
        "id": "5d772a47374649ee9da2102a4edcaabb",
        "platform": "AtCoder",
        "title": "AtCoder Beginner Contest 401",
        "url": "https://atcoder.jp/contests/abc401",
        "start_time": "2025-04-12T21:00:00+09:00",
        "duration": 6000
    },
    {
        "id": "313f2ae528e54446b3edba2688582f23",
        "platform": "AtCoder",
        "title": "Tokio Marine & Nichido Fire Insurance Programming Contest 2025  (AtCoder Beginner Contest 355)",
        "url": "https://atcoder.jp/contests/abc402",
        "start_time": "2025-04-19T21:00:00+09:00",
        "duration": 6000
    },
    {
        "id": "04f9ea30f7f344f489d51111397ff9fc",
        "platform": "AtCoder",
        "title": "AtCoder Grand Contest 072",
        "url": "https://atcoder.jp/contests/agc072",
        "start_time": "2025-04-20T21:00:00+09:00",
        "duration": 10800
    },
    {
        "id": "9f07f5699fcc4a37b096ccf72c4b4962",
        "platform": "AtCoder",
        "title": "BrainPad Programming Contest 2025 \uff08AtCoder Heuristic Contest 046\uff09",
        "url": "https://atcoder.jp/contests/ahc046",
        "start_time": "2025-04-26T15:00:00+09:00",
        "duration": 14400
    },
    {
        "id": "29046a870f544f0cae543e11ed921436",
        "platform": "AtCoder",
        "title": "AtCoder Beginner Contest 410",
        "url": "https://atcoder.jp/contests/abc410",
        "start_time": "2025-06-14T21:00:00+09:00",
        "duration": 6000
    },
    {
        "id": "83abb4ca319941abba35fd66459a9898",
        "platform": "AtCoder",
        "title": "World Tour Finals 2025 Algorithm",
        "url": "https://atcoder.jp/contests/awtf2025algo",
        "start_time": "2025-07-17T12:00:00+09:00",
        "duration": 18000
    },
    {
        "id": "6de765b0523d4c2abad2de7a92264d23",
        "platform": "AtCoder",
        "title": "World Tour Finals 2025 Algorithm\uff08Open Contest\uff09",
        "url": "https://atcoder.jp/contests/awtf2025algo-open",
        "start_time": "2025-07-17T12:00:00+09:00",
        "duration": 18000
    }
]