[
    {
        "id": "3f8892ab4dc94514ad6a3607725b7af9",
        "platform": "CodeChef",
        "title": "Starters 191",
        "url": "https://www.codechef.com/START191",
        "start_time": "2025-06-18T20:00:00+05:30",
        "duration": 7200
    },
    {
        "id": "19462e4be72941f4a9622cba620a85cd",
        "platform": "Codeforces",
        "title": "Codeforces Round (Div. 1 + Div. 2)",
        "url": "https://codeforces.com/contests/2122",
        "start_time": "2025-07-19T20:05:00+05:30",
        "duration": 9000
    },
    {
        "id": "31233bd4d0c24c388b759944d7b89cf7",
        "platform": "Codeforces",
        "title": "Codeforces Round (Div. 2)",
        "url": "https://codeforces.com/contests/2119",
        "start_time": "2025-07-05T20:05:00+05:30",
        "duration": 7200
    },
    {
        "id": "13c715517c754878abb22ec6b47e5695",
        "platform": "Codeforces",
        "title": "Educational Codeforces Round 180 (Rated for Div. 2)",
        "url": "https://codeforces.com/contests/2112",
        "start_time": "2025-06-23T20:05:00+05:30",
        "duration": 7200
    },
    {
        "id": "73a7c4c25a854643bf7589cc384d1361",
        "platform": "Codeforces",
        "title": "Codeforces Round (Div. 1 + Div. 2)",
        "url": "https://codeforces.com/contests/2120",
        "start_time": "2025-06-21T20:05:00+05:30",
        "duration": 9000
    },
    {
        "id": "6a2e7ce2967e4f058b2829d254ad1b42",
        "platform": "Codeforces",
        "title": "Codeforces Round 1032 (Div. 3)",
        "url": "https://codeforces.com/contests/2121",
        "start_time": "2025-06-17T20:05:00+05:30",
        "duration": 8100
    },
    {
        "id": "6400dabc36144aa58aada1695c42ded5",
        "platform": "Codeforces",
        "title": "Codeforces Round 1031 (Div. 2)",
        "url": "https://codeforces.com/contests/2113",
        "start_time": "2025-06-15T14:35:00+05:30",
        "duration": 7200
    },
    {
        "id": "ab7e0f4b016d477581914d01aa3826e8",
        "platform": "GeeksforGeeks",
        "title": "Job-A-thon 46 Hiring Challenge",
        "url": "https://practice.geeksforgeeks.org/contest/job-a-thon-46-hiring-challenge",
        "start_time": "2025-08-22T01:30:00+05:30",
        "duration": 9000
    },
    {
        "id": "50ac4cafb4e64d4aaa42e018e1816e2e",
        "platform": "LeetCode",
        "title": "Weekly Contest 459",
        "url": "https://leetcode.com/contest/weekly-contest-459",
        "start_time": "2025-07-20T08:00:00+05:30",
        "duration": 5400
    },
    {
        "id": "85c1dfd871474b78aec57cf148843605",
        "platform": "LeetCode",
        "title": "Biweekly Contest 161",
        "url": "https://leetcode.com/contest/biweekly-contest-161",
        "start_time": "2025-07-19T20:00:00+05:30",
        "duration": 5400
    },
    {
        "id": "535da6ae5ff94f8ca237265fca3b52f7",
        "platform": "LeetCode",
        "title": "Weekly Contest 458",
        "url": "https://leetcode.com/contest/weekly-contest-458",
        "start_time": "2025-07-13T08:00:00+05:30",
        "duration": 5400
    },
    {
        "id": "98b490b92ace44c3b7a4c340e71921ea",
        "platform": "LeetCode",
        "title": "Weekly Contest 457",
        "url": "https://leetcode.com/contest/weekly-contest-457",
        "start_time": "2025-07-06T08:00:00+05:30",
        "duration": 5400
    },
    {
        "id": "3b199d465f0a47398ea18aef36d7d586",
        "platform": "LeetCode",
        "title": "Biweekly Contest 160",
        "url": "https://leetcode.com/contest/biweekly-contest-160",
        "start_time": "2025-07-05T20:00:00+05:30",
        "duration": 5400
    },
    {
        "id": "d5fd208058444836a4268a282fef30d5",
        "platform": "LeetCode",
        "title": "Weekly Contest 456",
        "url": "https://leetcode.com/contest/weekly-contest-456",
        "start_time": "2025-06-29T08:00:00+05:30",
        "duration": 5400
    },
    {
        "id": "4dd254fd15684cbe86db8474743d7c1f",
        "platform": "LeetCode",
        "title": "Weekly Contest 455",
        "url": "https://leetcode.com/contest/weekly-contest-455",
        "start_time": "2025-06-22T08:00:00+05:30",
        "duration": 5400
    },
    {
        "id": "ede4941552cb4e2a82f61d9b1b13075e",
        "platform": "LeetCode",
        "title": "Biweekly Contest 159",
        "url": "https://leetcode.com/contest/biweekly-contest-159",
        "start_time": "2025-06-21T20:00:00+05:30",
        "duration": 5400
    },
    {
        "id": "d72e501cc74a4c1880db085dda6535c8",
        "platform": "HackerEarth",
        "title": "Shell.ai Hackathon 2025",
        "url": "https://www.hackerearth.com/challenges/competitive/shellai-hackathon-2025/",
        "start_time": "2025-07-04T12:30:00",
        "duration": 1641600
    },
    {
        "id": "b5483a1987f7422a97246e2e35189f07",
        "platform": "AtCoder",
        "title": "AtCoder Regular Contest 200 (Div. 2)",
        "url": "https://atcoder.jp/contests/arc200",
        "start_time": "2025-06-15T21:00:00+09:00",
        "duration": 7200
    },
    {
        "id": "05ffd037405045c4b91d3872890f2a2d",
        "platform": "AtCoder",
        "title": "Toyota Programming Contest 2025#3\uff08AtCoder Heuristic Contest 049\uff09",
        "url": "https://atcoder.jp/contests/ahc049",
        "start_time": "2025-06-21T15:00:00+09:00",
        "duration": 14400
    },
    {
        "id": "493df50b68e745848821c5e0d74faca6",
        "platform": "AtCoder",
        "title": "UNIQUE VISION Programming Contest 2025 Summer (AtCoder Beginner Contest 411)",
        "url": "https://atcoder.jp/contests/abc411",
        "start_time": "2025-06-21T21:00:00+09:00",
        "duration": 6000
    },
    {
        "id": "bc05a1c373da4c288e5310e81706008d",
        "platform": "AtCoder",
        "title": "AtCoder Regular Contest 201",
        "url": "https://atcoder.jp/contests/arc201",
        "start_time": "2025-06-22T21:00:00+09:00",
        "duration": 7200
    },
    {
        "id": "380148bb52bc41459beae6c5e047ada7",
        "platform": "AtCoder",
        "title": "AtCoder Beginner Contest 412",
        "url": "https://atcoder.jp/contests/abc412",
        "start_time": "2025-06-28T21:00:00+09:00",
        "duration": 6000
    },
    {
        "id": "d7184c6609df4d7da009140fdac17738",
        "platform": "AtCoder",
        "title": "Denso Create Programming Contest 2025\uff08AtCoder Beginner Contest 413\uff09",
        "url": "https://atcoder.jp/contests/abc413",
        "start_time": "2025-07-05T21:00:00+09:00",
        "duration": 6000
    },
    {
        "id": "e9d3e9b558f64bc893628ef8ec282c24",
        "platform": "AtCoder",
        "title": "World Tour Finals 2025 Algorithm",
        "url": "https://atcoder.jp/contests/awtf2025algo",
        "start_time": "2025-07-17T12:00:00+09:00",
        "duration": 18000
    },
    {
        "id": "4d5181b34ce54b5ca2453871e474af22",
        "platform": "AtCoder",
        "title": "World Tour Finals 2025 Algorithm\uff08Open Contest\uff09",
        "url": "https://atcoder.jp/contests/awtf2025algo-open",
        "start_time": "2025-07-17T12:00:00+09:00",
        "duration": 18000
    }
]