[
    {
        "id": "2bcdb953a8944ae881630d44e9c823fd",
        "platform": "CodeChef",
        "title": "Weekend Dev Challenge 44: Cybersecurity",
        "url": "https://www.codechef.com/DEVWEEKEND44",
        "start_time": "2026-04-04T00:00:00+05:30",
        "duration": 172800
    },
    {
        "id": "672198c2c504459a90111cb05878d029",
        "platform": "CodeChef",
        "title": "Monday Munch - DSA Challenge 32",
        "url": "https://www.codechef.com/DSAMONDAY32",
        "start_time": "2026-04-06T18:00:00+05:30",
        "duration": 10800
    },
    {
        "id": "005e0d35b8a94c0eb75eb7a86515a343",
        "platform": "CodeChef",
        "title": "Starters 233",
        "url": "https://www.codechef.com/START233",
        "start_time": "2026-04-08T20:00:00+05:30",
        "duration": 7200
    },
    {
        "id": "227f90d953fe4c5b9ceaa773712554d1",
        "platform": "CodeChef",
        "title": "Starters 234",
        "url": "https://www.codechef.com/START234",
        "start_time": "2026-04-15T20:00:00+05:30",
        "duration": 7200
    },
    {
        "id": "01cece68157a4ae08ec3eab1e05c03f0",
        "platform": "CodeChef",
        "title": "Starters 235",
        "url": "https://www.codechef.com/START235",
        "start_time": "2026-04-22T20:00:00+05:30",
        "duration": 7200
    },
    {
        "id": "1c8d7e8d18b144b5ac862db5cd27964b",
        "platform": "CodeChef",
        "title": "Starters 236",
        "url": "https://www.codechef.com/START236",
        "start_time": "2026-04-29T20:00:00+05:30",
        "duration": 7200
    },
    {
        "id": "59d00bd044a748ed9e6fa5d644fd8b62",
        "platform": "Codeforces",
        "title": "Codeforces Round (Div. 2)",
        "url": "https://codeforces.com/contests/2217",
        "start_time": "2026-04-07T20:05:00+05:30",
        "duration": 8100
    },
    {
        "id": "6c7624fcdbb94376805740fbc93de954",
        "platform": "Codeforces",
        "title": "Codeforces Round 1090 (Div. 4)",
        "url": "https://codeforces.com/contests/2218",
        "start_time": "2026-04-04T20:05:00+05:30",
        "duration": 8100
    },
    {
        "id": "b70c3f60dfac44e59762d5832ed3d297",
        "platform": "LeetCode",
        "title": "Biweekly Contest 180",
        "url": "https://leetcode.com/contest/biweekly-contest-180",
        "start_time": "2026-04-11T20:00:00+05:30",
        "duration": 5400
    },
    {
        "id": "1ab5cfd7846b4c19854dd8d37d73de82",
        "platform": "LeetCode",
        "title": "Weekly Contest 496",
        "url": "https://leetcode.com/contest/weekly-contest-496",
        "start_time": "2026-04-05T08:00:00+05:30",
        "duration": 5400
    },
    {
        "id": "92a4ea39f07b4b399e80082114608881",
        "platform": "AtCoder",
        "title": "AtCoder Beginner Contest 452",
        "url": "https://atcoder.jp/contests/abc452",
        "start_time": "2026-04-04T21:00:00+09:00",
        "duration": 6000
    },
    {
        "id": "7169c1c148aa4ab4ae003dfb30d2783c",
        "platform": "AtCoder",
        "title": "AtCoder Regular Contest 217",
        "url": "https://atcoder.jp/contests/arc217",
        "start_time": "2026-04-05T21:00:00+09:00",
        "duration": 7200
    },
    {
        "id": "6fd371a2428f4ccfb4ca3da7a64bfea0",
        "platform": "AtCoder",
        "title": "AtCoder Beginner Contest 453",
        "url": "https://atcoder.jp/contests/abc453",
        "start_time": "2026-04-11T21:00:00+09:00",
        "duration": 6000
    },
    {
        "id": "fed4bebe2eb24ae190fe1d9784a63436",
        "platform": "AtCoder",
        "title": "Keysight Technologies Programming Contest\uff08AtCoder Beginner Contest 454\uff09",
        "url": "https://atcoder.jp/contests/abc454",
        "start_time": "2026-04-18T21:00:00+09:00",
        "duration": 6000
    },
    {
        "id": "b219758482d140c3bdbbf17801ed0296",
        "platform": "AtCoder",
        "title": "\uff33\uff4b\uff59 Inc, Programming Contest 2026 (AtCoder Beginner Contest 455)",
        "url": "https://atcoder.jp/contests/abc455",
        "start_time": "2026-04-25T21:00:00+09:00",
        "duration": 6000
    },
    {
        "id": "611fbe4d6dac43be8b8915c2f3c815cd",
        "platform": "AtCoder",
        "title": "JR WEST and ALGO ARTIS Programming Contest  (AtCoder Heuristic Contest 064)",
        "url": "https://atcoder.jp/contests/ahc064",
        "start_time": "2026-04-26T15:00:00+09:00",
        "duration": 14400
    }
]