[
    {
        "id": "c5b91a8ecf1f4554bc950ab6d33f68f0",
        "platform": "Codeforces",
        "title": "Educational Codeforces Round 183 (Rated for Div. 2)",
        "url": "https://codeforces.com/contests/2145",
        "start_time": "2025-09-29T20:05:00+05:30",
        "duration": 7200
    },
    {
        "id": "f0ebafd70feb459085bc976db9ab9c87",
        "platform": "Codeforces",
        "title": "Codeforces Round (Div. 2)",
        "url": "https://codeforces.com/contests/2143",
        "start_time": "2025-09-17T20:05:00+05:30",
        "duration": 7200
    },
    {
        "id": "7da5c436abba419bbb0c8ad94035f6bc",
        "platform": "Codeforces",
        "title": "Educational Codeforces Round 182 (Rated for Div. 2)",
        "url": "https://codeforces.com/contests/2144",
        "start_time": "2025-09-15T20:05:00+05:30",
        "duration": 7200
    },
    {
        "id": "97dde91ef02040ffaf6b21a8d1026b4d",
        "platform": "Codeforces",
        "title": "Kotlin Heroes: Episode 13",
        "url": "https://codeforces.com/contests/2141",
        "start_time": "2025-09-12T20:05:00+05:30",
        "duration": 9000
    },
    {
        "id": "09f6e39c135042acb2bd11a2f5fe7272",
        "platform": "Codeforces",
        "title": "Codeforces Round (Div. 2)",
        "url": "https://codeforces.com/contests/2140",
        "start_time": "2025-09-09T20:05:00+05:30",
        "duration": 7200
    },
    {
        "id": "b1f90a3a82574a739d777a48b46a5e46",
        "platform": "Codeforces",
        "title": "Codeforces Round 1048 (Div. 1)",
        "url": "https://codeforces.com/contests/2138",
        "start_time": "2025-09-08T20:05:00+05:30",
        "duration": 10800
    },
    {
        "id": "5dad3567d87f4fbfbcbd210fd0385bd7",
        "platform": "Codeforces",
        "title": "Codeforces Round 1048 (Div. 2)",
        "url": "https://codeforces.com/contests/2139",
        "start_time": "2025-09-08T20:05:00+05:30",
        "duration": 10800
    },
    {
        "id": "faaf3e88e799422bb24096bb656fb0b4",
        "platform": "Codeforces",
        "title": "Codeforces Round 1047 (Div. 3)",
        "url": "https://codeforces.com/contests/2137",
        "start_time": "2025-09-07T20:05:00+05:30",
        "duration": 8100
    },
    {
        "id": "1990d68cfe394950b7b55a090c5b536d",
        "platform": "Codeforces",
        "title": "Kotlin Heroes: Practice 13",
        "url": "https://codeforces.com/contests/2142",
        "start_time": "2025-09-02T20:00:00+05:30",
        "duration": 864000
    },
    {
        "id": "e146dc0ed82b4e18a6f1adbe694ea978",
        "platform": "GeeksforGeeks",
        "title": "Verbal Ability (Part 1)",
        "url": "https://practice.geeksforgeeks.org/contest/verbal-ability-part-1",
        "start_time": "2025-09-02T05:30:00+05:30",
        "duration": 32011891200
    },
    {
        "id": "3b59a7d7331b4dc3b1828329839c0fc7",
        "platform": "GeeksforGeeks",
        "title": "Job-A-thon 47 Hiring Challenge",
        "url": "https://practice.geeksforgeeks.org/contest/job-a-thon-47-hiring-challenge-1304",
        "start_time": "2025-11-22T01:30:00+05:30",
        "duration": 9000
    },
    {
        "id": "71d36326cb5442cfa73b14976cf522fc",
        "platform": "LeetCode",
        "title": "Weekly Contest 467",
        "url": "https://leetcode.com/contest/weekly-contest-467",
        "start_time": "2025-09-14T08:00:00+05:30",
        "duration": 5400
    },
    {
        "id": "85963ded2fa344928177c32dbfb68e7c",
        "platform": "LeetCode",
        "title": "Biweekly Contest 165",
        "url": "https://leetcode.com/contest/biweekly-contest-165",
        "start_time": "2025-09-13T20:00:00+05:30",
        "duration": 5400
    },
    {
        "id": "947a503d48974e0b98c7e4ef95f32907",
        "platform": "LeetCode",
        "title": "Weekly Contest 466",
        "url": "https://leetcode.com/contest/weekly-contest-466",
        "start_time": "2025-09-07T08:00:00+05:30",
        "duration": 5400
    },
    {
        "id": "772ccc8194f04e87a224c5d138d0eed5",
        "platform": "AtCoder",
        "title": "AtCoder Regular Contest 205 (Div. 2)",
        "url": "https://atcoder.jp/contests/arc205",
        "start_time": "2025-09-06T21:00:00+09:00",
        "duration": 7200
    },
    {
        "id": "a29c2bb4d6314230bf546d6db546d5bb",
        "platform": "AtCoder",
        "title": "AtCoder Beginner Contest 422",
        "url": "https://atcoder.jp/contests/abc422",
        "start_time": "2025-09-07T13:10:00+09:00",
        "duration": 6000
    },
    {
        "id": "13f07db5a027487598fb1e7dbed49c78",
        "platform": "AtCoder",
        "title": "\u65e5\u672c\u6700\u5f37\u30d7\u30ed\u30b0\u30e9\u30de\u30fc\u5b66\u751f\u9078\u624b\u6a29\uff5eAdvance\uff5e",
        "url": "https://atcoder.jp/contests/jsc2025advance-final",
        "start_time": "2025-09-07T13:10:00+09:00",
        "duration": 6000
    },
    {
        "id": "f2083dc4ecc84d6294249473411ec453",
        "platform": "AtCoder",
        "title": "12th Asprova Programming Contest\uff08AtCoder Heuristic Contest 053\uff09",
        "url": "https://atcoder.jp/contests/ahc053",
        "start_time": "2025-09-13T19:00:00+09:00",
        "duration": 14400
    },
    {
        "id": "cd9e303d145446c19b50d7849ff5ba88",
        "platform": "AtCoder",
        "title": "AtCoder Beginner Contest 423",
        "url": "https://atcoder.jp/contests/abc423",
        "start_time": "2025-09-14T21:00:00+09:00",
        "duration": 6000
    },
    {
        "id": "c7c6975a85d549ce97a5c455c3856fcc",
        "platform": "AtCoder",
        "title": "ALGO ARTIS Programming Contest 2025 Summer\uff08AtCoder Heuristic Contest 054\uff09",
        "url": "https://atcoder.jp/contests/ahc054",
        "start_time": "2025-09-19T19:00:00+09:00",
        "duration": 864000
    },
    {
        "id": "5f85de734e95411ca156729ba84113d9",
        "platform": "AtCoder",
        "title": "AtCoder \u00d7 Engineer Guild\uff08AtCoder Beginner Contest 424\uff09",
        "url": "https://atcoder.jp/contests/abc424",
        "start_time": "2025-09-20T21:00:00+09:00",
        "duration": 6000
    },
    {
        "id": "43d1e6b0a13a4f219373699895de2db3",
        "platform": "AtCoder",
        "title": "AtCoder Regular Contest 206 (Div. 2)",
        "url": "https://atcoder.jp/contests/arc206",
        "start_time": "2025-09-21T21:00:00+09:00",
        "duration": 7200
    },
    {
        "id": "63757c7304e14973ac0793cd8c0d0e80",
        "platform": "AtCoder",
        "title": "UNIQUE VISION Programming Contest 2024 Autumn (AtCoder Beginner Contest 425)",
        "url": "https://atcoder.jp/contests/abc425",
        "start_time": "2025-09-27T21:00:00+09:00",
        "duration": 6000
    },
    {
        "id": "f330dd5cf26943dd89037d1d2b7b49da",
        "platform": "AtCoder",
        "title": "AtCoder Grand Contest 073",
        "url": "https://atcoder.jp/contests/agc073",
        "start_time": "2025-09-28T21:00:00+09:00",
        "duration": 10800
    },
    {
        "id": "46ebb4f89e4f433c9b21eb29709fd7be",
        "platform": "AtCoder",
        "title": "AtCoder Regular Contest 207 (Div.1)",
        "url": "https://atcoder.jp/contests/arc207",
        "start_time": "2025-10-05T21:00:00+09:00",
        "duration": 9000
    },
    {
        "id": "aea5af4eb31c4768a0087a3f3519029a",
        "platform": "AtCoder",
        "title": "Panasonic Programming Contest 2025\uff08AtCoder Beginner Contest 427\uff09",
        "url": "https://atcoder.jp/contests/abc427",
        "start_time": "2025-10-11T21:00:00+09:00",
        "duration": 6000
    }
]